eitaabot/__init__.py
eitaabot/api.py
eitaa_bot_amir-1.0.0.dist-info/LICENSE
eitaa_bot_amir-1.0.0.dist-info/METADATA
eitaa_bot_amir-1.0.0.dist-info/WHEEL
eitaa_bot_amir-1.0.0.dist-info/top_level.txt
eitaa_bot_amir-1.0.0.dist-info/RECORD
