Metadata-Version: 2.1
Name: eitaa-bot-amir
Version: 1.0.0
Summary: A Python package for interacting with Eitaa Bot API
Home-page: https://github.com/amirhossinpython/eitaabot
Author: AmirhossiKhazai
Author-email: amirhossinpython03@gmail.com
Classifier: Programming Language :: Python :: 3
Classifier: License :: OSI Approved :: MIT License
Classifier: Operating System :: OS Independent
License-File: LICENSE
Requires-Dist: requests
